tomate/__init__.py
tomate/accessor.py
tomate/constructor.py
tomate/custom_types.py
tomate/data_base.py
tomate/data_write.py
tomate/log.py
tomate/scope.py
tomate/variable_base.py
tomate/variables_info.py
tomate/coordinates/__init__.py
tomate/coordinates/coord.py
tomate/coordinates/coord_str.py
tomate/coordinates/latlon.py
tomate/coordinates/time.py
tomate/coordinates/variables.py
tomate/db_types/__init__.py
tomate/db_types/data_compute.py
tomate/db_types/data_disk.py
tomate/db_types/plotting/__init__.py
tomate/db_types/plotting/average_abc.py
tomate/db_types/plotting/contour.py
tomate/db_types/plotting/data_plot.py
tomate/db_types/plotting/image.py
tomate/db_types/plotting/image_abc.py
tomate/db_types/plotting/image_average.py
tomate/db_types/plotting/line.py
tomate/db_types/plotting/line_average.py
tomate/db_types/plotting/plot_object.py
tomate/db_types/plotting/scatter.py
tomate/filegroup/__init__.py
tomate/filegroup/command.py
tomate/filegroup/coord_scan.py
tomate/filegroup/filegroup_load.py
tomate/filegroup/filegroup_netcdf.py
tomate/filegroup/filegroup_scan.py
tomate/filegroup/matcher.py
tomate/filegroup/scanner.py
tomate/filegroup/spec.py
tomate/keys/__init__.py
tomate/keys/key.py
tomate/keys/keyring.py
tomate/scan_library/__init__.py
tomate/scan_library/general.py
tomate/scan_library/nc.py
tomate/var_types/__init__.py
tomate/var_types/variable_masked.py
tomate_data-2.2.2.dist-info/LICENSE
tomate_data-2.2.2.dist-info/METADATA
tomate_data-2.2.2.dist-info/WHEEL
tomate_data-2.2.2.dist-info/top_level.txt
tomate_data-2.2.2.dist-info/RECORD
