Metadata-Version: 2.1
Name: tomate-data
Version: 2.2.2
Summary: Tool to manipulate and aggregate data
Home-page: http://github.com/Descanonge/tomate
Author: Clément HAËCK
Author-email: clement.haeck@posteo.net
License: UNKNOWN
Project-URL: Documentation, https://tomate.readthedocs.org
Project-URL: Source, https://github.com/Descanonge/tomate
Keywords: data manipulate coordinate file netcdf load
Platform: UNKNOWN
Classifier: Development Status :: 5 - Production/Stable
Classifier: Intended Audience :: Science/Research
Classifier: License :: OSI Approved :: MIT License
Classifier: Programming Language :: Python :: 3.7
Classifier: Programming Language :: Python :: 3.8
Requires-Python: >=3.7
Requires-Dist: numpy
Provides-Extra: compute
Requires-Dist: scipy ; extra == 'compute'
Provides-Extra: netcdf
Requires-Dist: netCDF4 ; extra == 'netcdf'
Provides-Extra: plot
Requires-Dist: matplotlib ; extra == 'plot'
Provides-Extra: time
Requires-Dist: cftime (>=1.1.3) ; extra == 'time'
